__init__.py
bounded_contexts_linter/__init__.py
bounded_contexts_linter/cli.py
bounded_contexts_linter/flake8_plugin.py
bounded_contexts_linter/main.py
bounded_contexts_linter/py.typed
bounded_contexts_linter/utils.py
bounded_contexts_linter-1.0.0.dist-info/METADATA
bounded_contexts_linter-1.0.0.dist-info/WHEEL
bounded_contexts_linter-1.0.0.dist-info/entry_points.txt
bounded_contexts_linter-1.0.0.dist-info/top_level.txt
bounded_contexts_linter-1.0.0.dist-info/RECORD
