Metadata-Version: 2.4
Name: bounded-contexts-linter
Version: 1.0.0
Summary: A static code analyzer that checks the isolation of bounded contexts in Domain-Driven Design (DDD) projects
Project-URL: Homepage, https://github.com/pavelmaksimov/bounded-contexts-linter
Project-URL: Bug Tracker, https://github.com/pavelmaksimov/bounded-contexts-linter/issues
Requires-Python: >=3.11
Provides-Extra: flake8
Requires-Dist: flake8>=7.2.0; extra == "flake8"
